PyIeJs/__init__.py
PyIeJs-0.0.2.dist-info/METADATA
PyIeJs-0.0.2.dist-info/WHEEL
PyIeJs-0.0.2.dist-info/top_level.txt
PyIeJs-0.0.2.dist-info/RECORD
