Metadata-Version: 2.1
Name: PyIeJs
Version: 0.0.2
Summary: Interop.SHDocVw
Home-page: https://gitee.com/Martin-word/PyIeJs
Author: Martin
Author-email: 1403951401@qq.com
License: UNKNOWN
Platform: UNKNOWN
Classifier: Programming Language :: Python :: 3
Classifier: License :: OSI Approved :: MIT License
Classifier: Operating System :: OS Independent
Requires-Python: >=3.6
